tuneflow_py/__init__.py
tuneflow_py/base_plugin.py
tuneflow_py/utils.py
tuneflow_py/descriptors/audio_plugin_descriptor.py
tuneflow_py/descriptors/clip_descriptor.py
tuneflow_py/descriptors/common.py
tuneflow_py/descriptors/param.py
tuneflow_py/descriptors/plugin.py
tuneflow_py/descriptors/text.py
tuneflow_py/descriptors/widget.py
tuneflow_py/models/audio_plugin.py
tuneflow_py/models/automation.py
tuneflow_py/models/clip.py
tuneflow_py/models/lyric.py
tuneflow_py/models/marker.py
tuneflow_py/models/note.py
tuneflow_py/models/song.py
tuneflow_py/models/tempo.py
tuneflow_py/models/time_signature.py
tuneflow_py/models/track.py
tuneflow_py/models/protos/song_pb2.py
tuneflow_py-0.8.4.dist-info/LICENSE
tuneflow_py-0.8.4.dist-info/METADATA
tuneflow_py-0.8.4.dist-info/WHEEL
tuneflow_py-0.8.4.dist-info/top_level.txt
tuneflow_py-0.8.4.dist-info/RECORD
