Metadata-Version: 2.1
Name: tuneflow-py
Version: 0.8.4
Summary: Implement your music models and algorithms directly in TuneFlow - The next-gen DAW for the AI era
Author-email: TuneFlow <contact@info.tuneflow.com>
Project-URL: Homepage, https://github.com/tuneflow/tuneflow-py
Project-URL: Bug Tracker, https://github.com/tuneflow/tuneflow-py/issues
Keywords: AI,music,DAW,TuneFlow,composition,songwriting,music production,music generation,music transcription,mixing,music theory,music information retrieval,MIR,music analysis,song analysis
Classifier: Programming Language :: Python :: 3
Classifier: License :: OSI Approved :: MIT License
Classifier: Operating System :: OS Independent
Requires-Python: >=3.7
License-File: LICENSE
Requires-Dist: protobuf (<=3.19.4)
Requires-Dist: nanoid (>=2.0.0)
Requires-Dist: numpy (>=1.19.0)
Requires-Dist: miditoolkit-light (>=0.1.19)
Requires-Dist: typing-extensions (>=4.5.0)
